iphone_sync/__init__.py
iphone_sync/__main__.py
iphone_sync/py.typed
iphone_sync/verify.py
iphone_sync-1.0.1.dist-info/licenses/LICENSE
iphone_sync-1.0.1.dist-info/METADATA
iphone_sync-1.0.1.dist-info/WHEEL
iphone_sync-1.0.1.dist-info/entry_points.txt
iphone_sync-1.0.1.dist-info/top_level.txt
iphone_sync-1.0.1.dist-info/RECORD
