Metadata-Version: 2.4
Name: iphone-sync
Version: 1.0.1
Summary: An open source CLI script for Windows to backup photos from your iPhone
Author-email: Pradish Bijukchhe <pradish@sandbox.com.np>
License: Copyright (c) 2025 Pradish Bijukchhe
Project-URL: Homepage, https://github.com/pradishb/iphone-sync
Project-URL: Issues, https://github.com/pradishb/iphone-sync/issues
Classifier: Programming Language :: Python :: 3
Requires-Python: >=3
License-File: LICENSE
Requires-Dist: opencv-python
Requires-Dist: pillow
Requires-Dist: pywin32
Requires-Dist: tqdm
Dynamic: license-file
